src/mybootstrap_core_itskovichanton/__main__.py
src/mybootstrap_core_itskovichanton/alerts.py
src/mybootstrap_core_itskovichanton/app.py
src/mybootstrap_core_itskovichanton/config.py
src/mybootstrap_core_itskovichanton/di.py
src/mybootstrap_core_itskovichanton/email_service.py
src/mybootstrap_core_itskovichanton/fr.py
src/mybootstrap_core_itskovichanton/utils.py
mybootstrap_core_itskovichanton-0.0.1.dist-info/METADATA
mybootstrap_core_itskovichanton-0.0.1.dist-info/WHEEL
mybootstrap_core_itskovichanton-0.0.1.dist-info/licenses/LICENCE
mybootstrap_core_itskovichanton-0.0.1.dist-info/RECORD
