Metadata-Version: 2.1
Name: mybootstrap_core_itskovichanton
Version: 0.0.1
Summary: My bootstrap app engine core classes
Project-URL: Homepage, https://github.com/itskovichanton/pycore
Author-email: Anton Itskovich <itskovichae@gmail.com>
License-File: LICENCE
Classifier: License :: OSI Approved :: MIT License
Classifier: Operating System :: OS Independent
Classifier: Programming Language :: Python :: 3
Requires-Python: >=3.7
